odoo/addons/edi_sale_input_oca/README.rst
odoo/addons/edi_sale_input_oca/__init__.py
odoo/addons/edi_sale_input_oca/__manifest__.py
odoo/addons/edi_sale_input_oca/components/__init__.py
odoo/addons/edi_sale_input_oca/components/process.py
odoo/addons/edi_sale_input_oca/demo/edi_exchange_type.xml
odoo/addons/edi_sale_input_oca/i18n/edi_sale_input_oca.pot
odoo/addons/edi_sale_input_oca/i18n/it.po
odoo/addons/edi_sale_input_oca/readme/CONTRIBUTORS.md
odoo/addons/edi_sale_input_oca/readme/CREDITS.md
odoo/addons/edi_sale_input_oca/readme/DESCRIPTION.md
odoo/addons/edi_sale_input_oca/static/description/icon.png
odoo/addons/edi_sale_input_oca/static/description/index.html
odoo/addons/edi_sale_input_oca/tests/__init__.py
odoo/addons/edi_sale_input_oca/tests/common.py
odoo/addons/edi_sale_input_oca/tests/test_process.py
odoo/addons/edi_sale_input_oca/wizard/__init__.py
odoo/addons/edi_sale_input_oca/wizard/sale_order_import.py
odoo_addon_edi_sale_input_oca-18.0.1.0.1.dist-info/METADATA
odoo_addon_edi_sale_input_oca-18.0.1.0.1.dist-info/WHEEL
odoo_addon_edi_sale_input_oca-18.0.1.0.1.dist-info/top_level.txt
odoo_addon_edi_sale_input_oca-18.0.1.0.1.dist-info/RECORD
